osparc_client/__init__.py
osparc_client/api_client.py
osparc_client/configuration.py
osparc_client/exceptions.py
osparc_client/rest.py
osparc_client/api/__init__.py
osparc_client/api/credits_api.py
osparc_client/api/files_api.py
osparc_client/api/meta_api.py
osparc_client/api/solvers_api.py
osparc_client/api/studies_api.py
osparc_client/api/users_api.py
osparc_client/api/wallets_api.py
osparc_client/models/__init__.py
osparc_client/models/body_abort_multipart_upload_v0_files_file_id_abort_post.py
osparc_client/models/body_complete_multipart_upload_v0_files_file_id_complete_post.py
osparc_client/models/body_upload_file_v0_files_content_put.py
osparc_client/models/client_file.py
osparc_client/models/client_file_upload_data.py
osparc_client/models/error_get.py
osparc_client/models/file.py
osparc_client/models/file_upload_completion_body.py
osparc_client/models/file_upload_data.py
osparc_client/models/get_credit_price.py
osparc_client/models/groups.py
osparc_client/models/http_validation_error.py
osparc_client/models/job.py
osparc_client/models/job_inputs.py
osparc_client/models/job_logs_map.py
osparc_client/models/job_metadata.py
osparc_client/models/job_metadata_update.py
osparc_client/models/job_outputs.py
osparc_client/models/job_status.py
osparc_client/models/links.py
osparc_client/models/log_link.py
osparc_client/models/meta.py
osparc_client/models/one_page_solver_port.py
osparc_client/models/one_page_study_port.py
osparc_client/models/page_file.py
osparc_client/models/page_job.py
osparc_client/models/page_solver.py
osparc_client/models/page_study.py
osparc_client/models/pricing_plan_classification.py
osparc_client/models/pricing_unit_get.py
osparc_client/models/profile.py
osparc_client/models/profile_update.py
osparc_client/models/running_state.py
osparc_client/models/service_pricing_plan_get.py
osparc_client/models/solver.py
osparc_client/models/solver_port.py
osparc_client/models/study.py
osparc_client/models/study_port.py
osparc_client/models/upload_links.py
osparc_client-0.8.3.dist-info/METADATA
osparc_client-0.8.3.dist-info/WHEEL
osparc_client-0.8.3.dist-info/top_level.txt
osparc_client-0.8.3.dist-info/RECORD
