Metadata-Version: 2.1
Name: osparc_client
Version: 0.8.3
Summary: osparc.io web API (dev)
Home-page: https://itisfoundation.github.io/osparc-simcore-clients/
Author: pcrespov, bisgaard-itis
Author-email: support@osparc.io
License: MIT
Keywords: OpenAPI,OpenAPI-Generator,osparc.io web API (dev)
Classifier: Development Status :: 3 - Alpha
Classifier: License :: OSI Approved :: MIT License
Classifier: Programming Language :: Python :: 3
Classifier: Operating System :: OS Independent
Classifier: Natural Language :: English
Requires-Dist: urllib3 >=1.15
Requires-Dist: six >=1.10
Requires-Dist: certifi
Requires-Dist: python-dateutil
